tsdoc0/__init__.py
tsdoc0/py.typed
tsdoc0/python/__init__.py
tsdoc0/python/activity_header.py
tsdoc0/python/activity_part.py
tsdoc0/python/answer_abstract.py
tsdoc0/python/answer_shape.py
tsdoc0/python/code_refactorable.py
tsdoc0/python/code_static.py
tsdoc0/python/comment_abstract.py
tsdoc0/python/comment_concrete.py
tsdoc0/python/comment_paragraph.py
tsdoc0/python/comment_run_your_code.py
tsdoc0/python/comment_section.py
tsdoc0/python/comment_sentence.py
tsdoc0/python/comment_turn_in_your_code.py
tsdoc0/python/error_type.py
tsdoc0/python/grammar.tx
tsdoc0/python/keywords.py
tsdoc0/python/line_blank.py
tsdoc0/python/model.py
tsdoc0/python/point_tricky.py
tsdoc0/python/question_abstract.py
tsdoc0/python/question_review.py
tsdoc0/python/question_shape.py
tsdoc0/python/question_structure.py
tsdoc0/python/question_structure_no.py
tsdoc0/python/segment.py
tsdoc0/python/solution_code.py
tsdoc0/python/solution_item.py
tsdoc0/python/solution_pseudocode.py
tsdoc0/python/solution_shape.py
tsdoc0/python/utils.py
tsdoc0/python/vocabulary.py
tsdoc0/python/vocabulary_term.py
tsdoc0/python/vocabulary_terms.csv
tsdoc0-0.40.0.dist-info/LICENSE
tsdoc0-0.40.0.dist-info/METADATA
tsdoc0-0.40.0.dist-info/WHEEL
tsdoc0-0.40.0.dist-info/entry_points.txt
tsdoc0-0.40.0.dist-info/RECORD
