Metadata-Version: 2.1
Name: tsdoc0
Version: 0.40.0
Summary: TSDoc is an embedded comment language for TechSmart code files.
Home-page: https://github.com/techsmartkids/tsedu
License: CC-BY-NC-ND-4.0
Author: Ryan Sobol
Author-email: ryan.sobol@techsmart.codes
Requires-Python: >=3.11,<3.12
Classifier: License :: Other/Proprietary License
Classifier: Programming Language :: Python :: 3
Classifier: Programming Language :: Python :: 3.11
Requires-Dist: attrs (>=23.1.0,<24.0.0)
Requires-Dist: textx (>=3.1.1,<4.0.0)
Project-URL: Repository, https://github.com/techsmartkids/tsedu
